offline_model_builder/__init__.py
offline_model_builder/common/__init__.py
offline_model_builder/common/read_write_s3.py
offline_model_builder/content_profile/__init__.py
offline_model_builder/content_profile/multiclass_image_classification/__init__.py
offline_model_builder/content_profile/multiclass_image_classification/build_train.py
offline_model_builder/content_profile/multiclass_image_classification/common/__init__.py
offline_model_builder/content_profile/multiclass_image_classification/common/callbacks/EpochCheckPoint.py
offline_model_builder/content_profile/multiclass_image_classification/common/callbacks/__init__.py
offline_model_builder/content_profile/multiclass_image_classification/common/io/HDF5DatasetGenerator.py
offline_model_builder/content_profile/multiclass_image_classification/common/io/HDF5DatasetWriter.py
offline_model_builder/content_profile/multiclass_image_classification/common/io/__init__.py
offline_model_builder/content_profile/multiclass_image_classification/common/nn/NeuralNetwork.py
offline_model_builder/content_profile/multiclass_image_classification/common/nn/Perceptron.py
offline_model_builder/content_profile/multiclass_image_classification/common/nn/__init__.py
offline_model_builder/content_profile/multiclass_image_classification/common/nn/conv/AlexNet.py
offline_model_builder/content_profile/multiclass_image_classification/common/nn/conv/MiniGoogLeNet.py
offline_model_builder/content_profile/multiclass_image_classification/common/nn/conv/__init__.py
offline_model_builder/content_profile/multiclass_image_classification/common/preprocessing/AspectAwarePreprocessor.py
offline_model_builder/content_profile/multiclass_image_classification/common/preprocessing/CropPreprocessor.py
offline_model_builder/content_profile/multiclass_image_classification/common/preprocessing/ImageToArrayPreprocessor.py
offline_model_builder/content_profile/multiclass_image_classification/common/preprocessing/MeanPreprocessor.py
offline_model_builder-0.2.49.dist-info/WHEEL
offline_model_builder-0.2.49.dist-info/METADATA
offline_model_builder-0.2.49.dist-info/RECORD
